request_params/__init__.py
request_params/params.py
request_params-0.0.3.dist-info/LICENSE
request_params-0.0.3.dist-info/METADATA
request_params-0.0.3.dist-info/WHEEL
request_params-0.0.3.dist-info/top_level.txt
request_params-0.0.3.dist-info/RECORD
